{"is_source_file": true, "format": "JavaScript", "description": "This file is a test setup file for configuring custom Jest matchers for testing DOM nodes, using the '@testing-library/jest-dom' library.", "external_files": ["@testing-library/jest-dom"], "external_methods": ["expect", "toHaveTextContent"], "published": [], "classes": [], "methods": [], "calls": ["import '@testing-library/jest-dom'"], "search-terms": ["setupTests.js", "jest-dom", "testing-library", "custom matchers", "Jest", "DOM node assertions"], "state": 2, "file_id": 6, "knowledge_revision": 24, "git_revision": "0fd50b45265ab78c26097d135c1369330c9cc22c", "ctags": [], "hash": "1a77571e1a8cf36018a41bcedf60db75", "format-version": 4, "code-base-name": "notes_frontend", "filename": "notes_frontend/src/setupTests.js", "revision_history": [{"24": "0fd50b45265ab78c26097d135c1369330c9cc22c"}]}